{"homebrew_version":null,"used_options":[],"unused_options":[],"built_as_bottle":true,"poured_from_bottle":true,"installed_as_dependency":false,"installed_on_request":true,"changed_files":null,"time":1501867724,"source_modified_time":998591634,"HEAD":null,"stdlib":null,"compiler":"clang","aliases":[],"runtime_dependencies":null,"source":{"path":"/Users/nnegusse/dotfiles/bin/homebrew/Library/Taps/homebrew/homebrew-core/Formula/corkscrew.rb","tap":"homebrew/core","spec":"stable","versions":{"stable":"2.0","devel":null,"head":null,"version_scheme":0}}}